[
  {
    "id": 32009042,
    "node_id": "MDEwOlJlcG9zaXRvcnkzMjAwOTA0Mg==",
    "name": "ace",
    "full_name": "strilets/ace",
    "private": false,
    "owner": {
      "login": "strilets",
      "id": 7560855,
      "node_id": "MDQ6VXNlcjc1NjA4NTU=",
      "avatar_url": "https://avatars.githubusercontent.com/u/7560855?v=4",
      "gravatar_id": "",
      "url": "https://api.github.com/users/strilets",
      "html_url": "https://github.com/strilets",
      "followers_url": "https://api.github.com/users/strilets/followers",
      "following_url": "https://api.github.com/users/strilets/following{/other_user}",
      "gists_url": "https://api.github.com/users/strilets/gists{/gist_id}",
      "starred_url": "https://api.github.com/users/strilets/starred{/owner}{/repo}",
      "subscriptions_url": "https://api.github.com/users/strilets/subscriptions",
      "organizations_url": "https://api.github.com/users/strilets/orgs",
      "repos_url": "https://api.github.com/users/strilets/repos",
      "events_url": "https://api.github.com/users/strilets/events{/privacy}",
      "received_events_url": "https://api.github.com/users/strilets/received_events",
      "type": "User",
      "site_admin": false
    },
    "html_url": "https://github.com/strilets/ace",
    "description": "Twitter bootstrap 3 admin template",
    "fork": true,
    "url": "https://api.github.com/repos/strilets/ace",
    "forks_url": "https://api.github.com/repos/strilets/ace/forks",
    "keys_url": "https://api.github.com/repos/strilets/ace/keys{/key_id}",
    "collaborators_url": "https://api.github.com/repos/strilets/ace/collaborators{/collaborator}",
    "teams_url": "https://api.github.com/repos/strilets/ace/teams",
    "hooks_url": "https://api.github.com/repos/strilets/ace/hooks",
    "issue_events_url": "https://api.github.com/repos/strilets/ace/issues/events{/number}",
    "events_url": "https://api.github.com/repos/strilets/ace/events",
    "assignees_url": "https://api.github.com/repos/strilets/ace/assignees{/user}",
    "branches_url": "https://api.github.com/repos/strilets/ace/branches{/branch}",
    "tags_url": "https://api.github.com/repos/strilets/ace/tags",
    "blobs_url": "https://api.github.com/repos/strilets/ace/git/blobs{/sha}",
    "git_tags_url": "https://api.github.com/repos/strilets/ace/git/tags{/sha}",
    "git_refs_url": "https://api.github.com/repos/strilets/ace/git/refs{/sha}",
    "trees_url": "https://api.github.com/repos/strilets/ace/git/trees{/sha}",
    "statuses_url": "https://api.github.com/repos/strilets/ace/statuses/{sha}",
    "languages_url": "https://api.github.com/repos/strilets/ace/languages",
    "stargazers_url": "https://api.github.com/repos/strilets/ace/stargazers",
    "contributors_url": "https://api.github.com/repos/strilets/ace/contributors",
    "subscribers_url": "https://api.github.com/repos/strilets/ace/subscribers",
    "subscription_url": "https://api.github.com/repos/strilets/ace/subscription",
    "commits_url": "https://api.github.com/repos/strilets/ace/commits{/sha}",
    "git_commits_url": "https://api.github.com/repos/strilets/ace/git/commits{/sha}",
    "comments_url": "https://api.github.com/repos/strilets/ace/comments{/number}",
    "issue_comment_url": "https://api.github.com/repos/strilets/ace/issues/comments{/number}",
    "contents_url": "https://api.github.com/repos/strilets/ace/contents/{+path}",
    "compare_url": "https://api.github.com/repos/strilets/ace/compare/{base}...{head}",
    "merges_url": "https://api.github.com/repos/strilets/ace/merges",
    "archive_url": "https://api.github.com/repos/strilets/ace/{archive_format}{/ref}",
    "downloads_url": "https://api.github.com/repos/strilets/ace/downloads",
    "issues_url": "https://api.github.com/repos/strilets/ace/issues{/number}",
    "pulls_url": "https://api.github.com/repos/strilets/ace/pulls{/number}",
    "milestones_url": "https://api.github.com/repos/strilets/ace/milestones{/number}",
    "notifications_url": "https://api.github.com/repos/strilets/ace/notifications{?since,all,participating}",
    "labels_url": "https://api.github.com/repos/strilets/ace/labels{/name}",
    "releases_url": "https://api.github.com/repos/strilets/ace/releases{/id}",
    "deployments_url": "https://api.github.com/repos/strilets/ace/deployments",
    "created_at": "2015-03-11T09:28:21Z",
    "updated_at": "2015-03-11T09:28:21Z",
    "pushed_at": "2014-12-28T13:22:47Z",
    "git_url": "git://github.com/strilets/ace.git",
    "ssh_url": "git@github.com:strilets/ace.git",
    "clone_url": "https://github.com/strilets/ace.git",
    "svn_url": "https://github.com/strilets/ace",
    "homepage": "ace.jeka.by",
    "size": 3310,
    "stargazers_count": 0,
    "watchers_count": 0,
    "language": "HTML",
    "has_issues": false,
    "has_projects": true,
    "has_downloads": true,
    "has_wiki": true,
    "has_pages": false,
    "forks_count": 0,
    "mirror_url": null,
    "archived": false,
    "disabled": false,
    "open_issues_count": 0,
    "license": {
      "key": "mit",
      "name": "MIT License",
      "spdx_id": "MIT",
      "url": "https://api.github.com/licenses/mit",
      "node_id": "MDc6TGljZW5zZTEz"
    },
    "forks": 0,
    "open_issues": 0,
    "watchers": 0,
    "default_branch": "master",
    "permissions": {
      "admin": false,
      "push": false,
      "pull": true
    }
  }
]