[
  {
    "id": 237295301,
    "node_id": "MDEwOlJlcG9zaXRvcnkyMzcyOTUzMDE=",
    "name": "journal",
    "full_name": "yamadote/journal",
    "private": false,
    "owner": {
      "login": "yamadote",
      "id": 33160770,
      "node_id": "MDQ6VXNlcjMzMTYwNzcw",
      "avatar_url": "https://avatars.githubusercontent.com/u/33160770?v=4",
      "gravatar_id": "",
      "url": "https://api.github.com/users/yamadote",
      "html_url": "https://github.com/yamadote",
      "followers_url": "https://api.github.com/users/yamadote/followers",
      "following_url": "https://api.github.com/users/yamadote/following{/other_user}",
      "gists_url": "https://api.github.com/users/yamadote/gists{/gist_id}",
      "starred_url": "https://api.github.com/users/yamadote/starred{/owner}{/repo}",
      "subscriptions_url": "https://api.github.com/users/yamadote/subscriptions",
      "organizations_url": "https://api.github.com/users/yamadote/orgs",
      "repos_url": "https://api.github.com/users/yamadote/repos",
      "events_url": "https://api.github.com/users/yamadote/events{/privacy}",
      "received_events_url": "https://api.github.com/users/yamadote/received_events",
      "type": "User",
      "site_admin": false
    },
    "html_url": "https://github.com/yamadote/journal",
    "description": ":rage4: App for personal task tracking",
    "fork": false,
    "url": "https://api.github.com/repos/yamadote/journal",
    "forks_url": "https://api.github.com/repos/yamadote/journal/forks",
    "keys_url": "https://api.github.com/repos/yamadote/journal/keys{/key_id}",
    "collaborators_url": "https://api.github.com/repos/yamadote/journal/collaborators{/collaborator}",
    "teams_url": "https://api.github.com/repos/yamadote/journal/teams",
    "hooks_url": "https://api.github.com/repos/yamadote/journal/hooks",
    "issue_events_url": "https://api.github.com/repos/yamadote/journal/issues/events{/number}",
    "events_url": "https://api.github.com/repos/yamadote/journal/events",
    "assignees_url": "https://api.github.com/repos/yamadote/journal/assignees{/user}",
    "branches_url": "https://api.github.com/repos/yamadote/journal/branches{/branch}",
    "tags_url": "https://api.github.com/repos/yamadote/journal/tags",
    "blobs_url": "https://api.github.com/repos/yamadote/journal/git/blobs{/sha}",
    "git_tags_url": "https://api.github.com/repos/yamadote/journal/git/tags{/sha}",
    "git_refs_url": "https://api.github.com/repos/yamadote/journal/git/refs{/sha}",
    "trees_url": "https://api.github.com/repos/yamadote/journal/git/trees{/sha}",
    "statuses_url": "https://api.github.com/repos/yamadote/journal/statuses/{sha}",
    "languages_url": "https://api.github.com/repos/yamadote/journal/languages",
    "stargazers_url": "https://api.github.com/repos/yamadote/journal/stargazers",
    "contributors_url": "https://api.github.com/repos/yamadote/journal/contributors",
    "subscribers_url": "https://api.github.com/repos/yamadote/journal/subscribers",
    "subscription_url": "https://api.github.com/repos/yamadote/journal/subscription",
    "commits_url": "https://api.github.com/repos/yamadote/journal/commits{/sha}",
    "git_commits_url": "https://api.github.com/repos/yamadote/journal/git/commits{/sha}",
    "comments_url": "https://api.github.com/repos/yamadote/journal/comments{/number}",
    "issue_comment_url": "https://api.github.com/repos/yamadote/journal/issues/comments{/number}",
    "contents_url": "https://api.github.com/repos/yamadote/journal/contents/{+path}",
    "compare_url": "https://api.github.com/repos/yamadote/journal/compare/{base}...{head}",
    "merges_url": "https://api.github.com/repos/yamadote/journal/merges",
    "archive_url": "https://api.github.com/repos/yamadote/journal/{archive_format}{/ref}",
    "downloads_url": "https://api.github.com/repos/yamadote/journal/downloads",
    "issues_url": "https://api.github.com/repos/yamadote/journal/issues{/number}",
    "pulls_url": "https://api.github.com/repos/yamadote/journal/pulls{/number}",
    "milestones_url": "https://api.github.com/repos/yamadote/journal/milestones{/number}",
    "notifications_url": "https://api.github.com/repos/yamadote/journal/notifications{?since,all,participating}",
    "labels_url": "https://api.github.com/repos/yamadote/journal/labels{/name}",
    "releases_url": "https://api.github.com/repos/yamadote/journal/releases{/id}",
    "deployments_url": "https://api.github.com/repos/yamadote/journal/deployments",
    "created_at": "2020-01-30T20:04:52Z",
    "updated_at": "2020-12-22T21:41:19Z",
    "pushed_at": "2020-12-22T21:41:17Z",
    "git_url": "git://github.com/yamadote/journal.git",
    "ssh_url": "git@github.com:yamadote/journal.git",
    "clone_url": "https://github.com/yamadote/journal.git",
    "svn_url": "https://github.com/yamadote/journal",
    "homepage": "",
    "size": 1228,
    "stargazers_count": 1,
    "watchers_count": 1,
    "language": "JavaScript",
    "has_issues": true,
    "has_projects": true,
    "has_downloads": true,
    "has_wiki": true,
    "has_pages": true,
    "forks_count": 0,
    "mirror_url": null,
    "archived": false,
    "disabled": false,
    "open_issues_count": 0,
    "license": null,
    "forks": 0,
    "open_issues": 0,
    "watchers": 1,
    "default_branch": "master",
    "permissions": {
      "admin": false,
      "push": false,
      "pull": true
    }
  },
  {
    "id": 181751915,
    "node_id": "MDEwOlJlcG9zaXRvcnkxODE3NTE5MTU=",
    "name": "file-manager",
    "full_name": "yamadote/file-manager",
    "private": false,
    "owner": {
      "login": "yamadote",
      "id": 33160770,
      "node_id": "MDQ6VXNlcjMzMTYwNzcw",
      "avatar_url": "https://avatars.githubusercontent.com/u/33160770?v=4",
      "gravatar_id": "",
      "url": "https://api.github.com/users/yamadote",
      "html_url": "https://github.com/yamadote",
      "followers_url": "https://api.github.com/users/yamadote/followers",
      "following_url": "https://api.github.com/users/yamadote/following{/other_user}",
      "gists_url": "https://api.github.com/users/yamadote/gists{/gist_id}",
      "starred_url": "https://api.github.com/users/yamadote/starred{/owner}{/repo}",
      "subscriptions_url": "https://api.github.com/users/yamadote/subscriptions",
      "organizations_url": "https://api.github.com/users/yamadote/orgs",
      "repos_url": "https://api.github.com/users/yamadote/repos",
      "events_url": "https://api.github.com/users/yamadote/events{/privacy}",
      "received_events_url": "https://api.github.com/users/yamadote/received_events",
      "type": "User",
      "site_admin": false
    },
    "html_url": "https://github.com/yamadote/file-manager",
    "description": ":file_folder: Library for working with local files and folders.",
    "fork": false,
    "url": "https://api.github.com/repos/yamadote/file-manager",
    "forks_url": "https://api.github.com/repos/yamadote/file-manager/forks",
    "keys_url": "https://api.github.com/repos/yamadote/file-manager/keys{/key_id}",
    "collaborators_url": "https://api.github.com/repos/yamadote/file-manager/collaborators{/collaborator}",
    "teams_url": "https://api.github.com/repos/yamadote/file-manager/teams",
    "hooks_url": "https://api.github.com/repos/yamadote/file-manager/hooks",
    "issue_events_url": "https://api.github.com/repos/yamadote/file-manager/issues/events{/number}",
    "events_url": "https://api.github.com/repos/yamadote/file-manager/events",
    "assignees_url": "https://api.github.com/repos/yamadote/file-manager/assignees{/user}",
    "branches_url": "https://api.github.com/repos/yamadote/file-manager/branches{/branch}",
    "tags_url": "https://api.github.com/repos/yamadote/file-manager/tags",
    "blobs_url": "https://api.github.com/repos/yamadote/file-manager/git/blobs{/sha}",
    "git_tags_url": "https://api.github.com/repos/yamadote/file-manager/git/tags{/sha}",
    "git_refs_url": "https://api.github.com/repos/yamadote/file-manager/git/refs{/sha}",
    "trees_url": "https://api.github.com/repos/yamadote/file-manager/git/trees{/sha}",
    "statuses_url": "https://api.github.com/repos/yamadote/file-manager/statuses/{sha}",
    "languages_url": "https://api.github.com/repos/yamadote/file-manager/languages",
    "stargazers_url": "https://api.github.com/repos/yamadote/file-manager/stargazers",
    "contributors_url": "https://api.github.com/repos/yamadote/file-manager/contributors",
    "subscribers_url": "https://api.github.com/repos/yamadote/file-manager/subscribers",
    "subscription_url": "https://api.github.com/repos/yamadote/file-manager/subscription",
    "commits_url": "https://api.github.com/repos/yamadote/file-manager/commits{/sha}",
    "git_commits_url": "https://api.github.com/repos/yamadote/file-manager/git/commits{/sha}",
    "comments_url": "https://api.github.com/repos/yamadote/file-manager/comments{/number}",
    "issue_comment_url": "https://api.github.com/repos/yamadote/file-manager/issues/comments{/number}",
    "contents_url": "https://api.github.com/repos/yamadote/file-manager/contents/{+path}",
    "compare_url": "https://api.github.com/repos/yamadote/file-manager/compare/{base}...{head}",
    "merges_url": "https://api.github.com/repos/yamadote/file-manager/merges",
    "archive_url": "https://api.github.com/repos/yamadote/file-manager/{archive_format}{/ref}",
    "downloads_url": "https://api.github.com/repos/yamadote/file-manager/downloads",
    "issues_url": "https://api.github.com/repos/yamadote/file-manager/issues{/number}",
    "pulls_url": "https://api.github.com/repos/yamadote/file-manager/pulls{/number}",
    "milestones_url": "https://api.github.com/repos/yamadote/file-manager/milestones{/number}",
    "notifications_url": "https://api.github.com/repos/yamadote/file-manager/notifications{?since,all,participating}",
    "labels_url": "https://api.github.com/repos/yamadote/file-manager/labels{/name}",
    "releases_url": "https://api.github.com/repos/yamadote/file-manager/releases{/id}",
    "deployments_url": "https://api.github.com/repos/yamadote/file-manager/deployments",
    "created_at": "2019-04-16T19:17:09Z",
    "updated_at": "2019-04-29T10:07:45Z",
    "pushed_at": "2019-04-16T19:22:53Z",
    "git_url": "git://github.com/yamadote/file-manager.git",
    "ssh_url": "git@github.com:yamadote/file-manager.git",
    "clone_url": "https://github.com/yamadote/file-manager.git",
    "svn_url": "https://github.com/yamadote/file-manager",
    "homepage": "",
    "size": 5,
    "stargazers_count": 0,
    "watchers_count": 0,
    "language": "PHP",
    "has_issues": true,
    "has_projects": true,
    "has_downloads": true,
    "has_wiki": true,
    "has_pages": false,
    "forks_count": 0,
    "mirror_url": null,
    "archived": false,
    "disabled": false,
    "open_issues_count": 0,
    "license": {
      "key": "mit",
      "name": "MIT License",
      "spdx_id": "MIT",
      "url": "https://api.github.com/licenses/mit",
      "node_id": "MDc6TGljZW5zZTEz"
    },
    "forks": 0,
    "open_issues": 0,
    "watchers": 0,
    "default_branch": "master",
    "permissions": {
      "admin": false,
      "push": false,
      "pull": true
    }
  },
  {
    "id": 181753214,
    "node_id": "MDEwOlJlcG9zaXRvcnkxODE3NTMyMTQ=",
    "name": "image-filters",
    "full_name": "yamadote/image-filters",
    "private": false,
    "owner": {
      "login": "yamadote",
      "id": 33160770,
      "node_id": "MDQ6VXNlcjMzMTYwNzcw",
      "avatar_url": "https://avatars.githubusercontent.com/u/33160770?v=4",
      "gravatar_id": "",
      "url": "https://api.github.com/users/yamadote",
      "html_url": "https://github.com/yamadote",
      "followers_url": "https://api.github.com/users/yamadote/followers",
      "following_url": "https://api.github.com/users/yamadote/following{/other_user}",
      "gists_url": "https://api.github.com/users/yamadote/gists{/gist_id}",
      "starred_url": "https://api.github.com/users/yamadote/starred{/owner}{/repo}",
      "subscriptions_url": "https://api.github.com/users/yamadote/subscriptions",
      "organizations_url": "https://api.github.com/users/yamadote/orgs",
      "repos_url": "https://api.github.com/users/yamadote/repos",
      "events_url": "https://api.github.com/users/yamadote/events{/privacy}",
      "received_events_url": "https://api.github.com/users/yamadote/received_events",
      "type": "User",
      "site_admin": false
    },
    "html_url": "https://github.com/yamadote/image-filters",
    "description": ":flower_playing_cards: Library for adding filters to images.",
    "fork": false,
    "url": "https://api.github.com/repos/yamadote/image-filters",
    "forks_url": "https://api.github.com/repos/yamadote/image-filters/forks",
    "keys_url": "https://api.github.com/repos/yamadote/image-filters/keys{/key_id}",
    "collaborators_url": "https://api.github.com/repos/yamadote/image-filters/collaborators{/collaborator}",
    "teams_url": "https://api.github.com/repos/yamadote/image-filters/teams",
    "hooks_url": "https://api.github.com/repos/yamadote/image-filters/hooks",
    "issue_events_url": "https://api.github.com/repos/yamadote/image-filters/issues/events{/number}",
    "events_url": "https://api.github.com/repos/yamadote/image-filters/events",
    "assignees_url": "https://api.github.com/repos/yamadote/image-filters/assignees{/user}",
    "branches_url": "https://api.github.com/repos/yamadote/image-filters/branches{/branch}",
    "tags_url": "https://api.github.com/repos/yamadote/image-filters/tags",
    "blobs_url": "https://api.github.com/repos/yamadote/image-filters/git/blobs{/sha}",
    "git_tags_url": "https://api.github.com/repos/yamadote/image-filters/git/tags{/sha}",
    "git_refs_url": "https://api.github.com/repos/yamadote/image-filters/git/refs{/sha}",
    "trees_url": "https://api.github.com/repos/yamadote/image-filters/git/trees{/sha}",
    "statuses_url": "https://api.github.com/repos/yamadote/image-filters/statuses/{sha}",
    "languages_url": "https://api.github.com/repos/yamadote/image-filters/languages",
    "stargazers_url": "https://api.github.com/repos/yamadote/image-filters/stargazers",
    "contributors_url": "https://api.github.com/repos/yamadote/image-filters/contributors",
    "subscribers_url": "https://api.github.com/repos/yamadote/image-filters/subscribers",
    "subscription_url": "https://api.github.com/repos/yamadote/image-filters/subscription",
    "commits_url": "https://api.github.com/repos/yamadote/image-filters/commits{/sha}",
    "git_commits_url": "https://api.github.com/repos/yamadote/image-filters/git/commits{/sha}",
    "comments_url": "https://api.github.com/repos/yamadote/image-filters/comments{/number}",
    "issue_comment_url": "https://api.github.com/repos/yamadote/image-filters/issues/comments{/number}",
    "contents_url": "https://api.github.com/repos/yamadote/image-filters/contents/{+path}",
    "compare_url": "https://api.github.com/repos/yamadote/image-filters/compare/{base}...{head}",
    "merges_url": "https://api.github.com/repos/yamadote/image-filters/merges",
    "archive_url": "https://api.github.com/repos/yamadote/image-filters/{archive_format}{/ref}",
    "downloads_url": "https://api.github.com/repos/yamadote/image-filters/downloads",
    "issues_url": "https://api.github.com/repos/yamadote/image-filters/issues{/number}",
    "pulls_url": "https://api.github.com/repos/yamadote/image-filters/pulls{/number}",
    "milestones_url": "https://api.github.com/repos/yamadote/image-filters/milestones{/number}",
    "notifications_url": "https://api.github.com/repos/yamadote/image-filters/notifications{?since,all,participating}",
    "labels_url": "https://api.github.com/repos/yamadote/image-filters/labels{/name}",
    "releases_url": "https://api.github.com/repos/yamadote/image-filters/releases{/id}",
    "deployments_url": "https://api.github.com/repos/yamadote/image-filters/deployments",
    "created_at": "2019-04-16T19:25:54Z",
    "updated_at": "2019-04-29T10:11:53Z",
    "pushed_at": "2019-04-16T19:26:53Z",
    "git_url": "git://github.com/yamadote/image-filters.git",
    "ssh_url": "git@github.com:yamadote/image-filters.git",
    "clone_url": "https://github.com/yamadote/image-filters.git",
    "svn_url": "https://github.com/yamadote/image-filters",
    "homepage": "",
    "size": 7,
    "stargazers_count": 0,
    "watchers_count": 0,
    "language": "PHP",
    "has_issues": true,
    "has_projects": true,
    "has_downloads": true,
    "has_wiki": true,
    "has_pages": false,
    "forks_count": 0,
    "mirror_url": null,
    "archived": false,
    "disabled": false,
    "open_issues_count": 0,
    "license": {
      "key": "mit",
      "name": "MIT License",
      "spdx_id": "MIT",
      "url": "https://api.github.com/licenses/mit",
      "node_id": "MDc6TGljZW5zZTEz"
    },
    "forks": 0,
    "open_issues": 0,
    "watchers": 0,
    "default_branch": "master",
    "permissions": {
      "admin": false,
      "push": false,
      "pull": true
    }
  },
  {
    "id": 183044410,
    "node_id": "MDEwOlJlcG9zaXRvcnkxODMwNDQ0MTA=",
    "name": "naveen",
    "full_name": "yamadote/naveen",
    "private": false,
    "owner": {
      "login": "yamadote",
      "id": 33160770,
      "node_id": "MDQ6VXNlcjMzMTYwNzcw",
      "avatar_url": "https://avatars.githubusercontent.com/u/33160770?v=4",
      "gravatar_id": "",
      "url": "https://api.github.com/users/yamadote",
      "html_url": "https://github.com/yamadote",
      "followers_url": "https://api.github.com/users/yamadote/followers",
      "following_url": "https://api.github.com/users/yamadote/following{/other_user}",
      "gists_url": "https://api.github.com/users/yamadote/gists{/gist_id}",
      "starred_url": "https://api.github.com/users/yamadote/starred{/owner}{/repo}",
      "subscriptions_url": "https://api.github.com/users/yamadote/subscriptions",
      "organizations_url": "https://api.github.com/users/yamadote/orgs",
      "repos_url": "https://api.github.com/users/yamadote/repos",
      "events_url": "https://api.github.com/users/yamadote/events{/privacy}",
      "received_events_url": "https://api.github.com/users/yamadote/received_events",
      "type": "User",
      "site_admin": false
    },
    "html_url": "https://github.com/yamadote/naveen",
    "description": ":bookmark_tabs: Just creating template from pdf",
    "fork": false,
    "url": "https://api.github.com/repos/yamadote/naveen",
    "forks_url": "https://api.github.com/repos/yamadote/naveen/forks",
    "keys_url": "https://api.github.com/repos/yamadote/naveen/keys{/key_id}",
    "collaborators_url": "https://api.github.com/repos/yamadote/naveen/collaborators{/collaborator}",
    "teams_url": "https://api.github.com/repos/yamadote/naveen/teams",
    "hooks_url": "https://api.github.com/repos/yamadote/naveen/hooks",
    "issue_events_url": "https://api.github.com/repos/yamadote/naveen/issues/events{/number}",
    "events_url": "https://api.github.com/repos/yamadote/naveen/events",
    "assignees_url": "https://api.github.com/repos/yamadote/naveen/assignees{/user}",
    "branches_url": "https://api.github.com/repos/yamadote/naveen/branches{/branch}",
    "tags_url": "https://api.github.com/repos/yamadote/naveen/tags",
    "blobs_url": "https://api.github.com/repos/yamadote/naveen/git/blobs{/sha}",
    "git_tags_url": "https://api.github.com/repos/yamadote/naveen/git/tags{/sha}",
    "git_refs_url": "https://api.github.com/repos/yamadote/naveen/git/refs{/sha}",
    "trees_url": "https://api.github.com/repos/yamadote/naveen/git/trees{/sha}",
    "statuses_url": "https://api.github.com/repos/yamadote/naveen/statuses/{sha}",
    "languages_url": "https://api.github.com/repos/yamadote/naveen/languages",
    "stargazers_url": "https://api.github.com/repos/yamadote/naveen/stargazers",
    "contributors_url": "https://api.github.com/repos/yamadote/naveen/contributors",
    "subscribers_url": "https://api.github.com/repos/yamadote/naveen/subscribers",
    "subscription_url": "https://api.github.com/repos/yamadote/naveen/subscription",
    "commits_url": "https://api.github.com/repos/yamadote/naveen/commits{/sha}",
    "git_commits_url": "https://api.github.com/repos/yamadote/naveen/git/commits{/sha}",
    "comments_url": "https://api.github.com/repos/yamadote/naveen/comments{/number}",
    "issue_comment_url": "https://api.github.com/repos/yamadote/naveen/issues/comments{/number}",
    "contents_url": "https://api.github.com/repos/yamadote/naveen/contents/{+path}",
    "compare_url": "https://api.github.com/repos/yamadote/naveen/compare/{base}...{head}",
    "merges_url": "https://api.github.com/repos/yamadote/naveen/merges",
    "archive_url": "https://api.github.com/repos/yamadote/naveen/{archive_format}{/ref}",
    "downloads_url": "https://api.github.com/repos/yamadote/naveen/downloads",
    "issues_url": "https://api.github.com/repos/yamadote/naveen/issues{/number}",
    "pulls_url": "https://api.github.com/repos/yamadote/naveen/pulls{/number}",
    "milestones_url": "https://api.github.com/repos/yamadote/naveen/milestones{/number}",
    "notifications_url": "https://api.github.com/repos/yamadote/naveen/notifications{?since,all,participating}",
    "labels_url": "https://api.github.com/repos/yamadote/naveen/labels{/name}",
    "releases_url": "https://api.github.com/repos/yamadote/naveen/releases{/id}",
    "deployments_url": "https://api.github.com/repos/yamadote/naveen/deployments",
    "created_at": "2019-04-23T15:29:31Z",
    "updated_at": "2019-04-29T10:09:36Z",
    "pushed_at": "2019-04-23T15:31:03Z",
    "git_url": "git://github.com/yamadote/naveen.git",
    "ssh_url": "git@github.com:yamadote/naveen.git",
    "clone_url": "https://github.com/yamadote/naveen.git",
    "svn_url": "https://github.com/yamadote/naveen",
    "homepage": "https://yamadote.github.io/naveen",
    "size": 4096,
    "stargazers_count": 0,
    "watchers_count": 0,
    "language": "CSS",
    "has_issues": true,
    "has_projects": true,
    "has_downloads": true,
    "has_wiki": true,
    "has_pages": true,
    "forks_count": 0,
    "mirror_url": null,
    "archived": false,
    "disabled": false,
    "open_issues_count": 0,
    "license": {
      "key": "mit",
      "name": "MIT License",
      "spdx_id": "MIT",
      "url": "https://api.github.com/licenses/mit",
      "node_id": "MDc6TGljZW5zZTEz"
    },
    "forks": 0,
    "open_issues": 0,
    "watchers": 0,
    "default_branch": "master",
    "permissions": {
      "admin": false,
      "push": false,
      "pull": true
    }
  },
  {
    "id": 291470679,
    "node_id": "MDEwOlJlcG9zaXRvcnkyOTE0NzA2Nzk=",
    "name": "phpstorm",
    "full_name": "yamadote/phpstorm",
    "private": false,
    "owner": {
      "login": "yamadote",
      "id": 33160770,
      "node_id": "MDQ6VXNlcjMzMTYwNzcw",
      "avatar_url": "https://avatars.githubusercontent.com/u/33160770?v=4",
      "gravatar_id": "",
      "url": "https://api.github.com/users/yamadote",
      "html_url": "https://github.com/yamadote",
      "followers_url": "https://api.github.com/users/yamadote/followers",
      "following_url": "https://api.github.com/users/yamadote/following{/other_user}",
      "gists_url": "https://api.github.com/users/yamadote/gists{/gist_id}",
      "starred_url": "https://api.github.com/users/yamadote/starred{/owner}{/repo}",
      "subscriptions_url": "https://api.github.com/users/yamadote/subscriptions",
      "organizations_url": "https://api.github.com/users/yamadote/orgs",
      "repos_url": "https://api.github.com/users/yamadote/repos",
      "events_url": "https://api.github.com/users/yamadote/events{/privacy}",
      "received_events_url": "https://api.github.com/users/yamadote/received_events",
      "type": "User",
      "site_admin": false
    },
    "html_url": "https://github.com/yamadote/phpstorm",
    "description": null,
    "fork": false,
    "url": "https://api.github.com/repos/yamadote/phpstorm",
    "forks_url": "https://api.github.com/repos/yamadote/phpstorm/forks",
    "keys_url": "https://api.github.com/repos/yamadote/phpstorm/keys{/key_id}",
    "collaborators_url": "https://api.github.com/repos/yamadote/phpstorm/collaborators{/collaborator}",
    "teams_url": "https://api.github.com/repos/yamadote/phpstorm/teams",
    "hooks_url": "https://api.github.com/repos/yamadote/phpstorm/hooks",
    "issue_events_url": "https://api.github.com/repos/yamadote/phpstorm/issues/events{/number}",
    "events_url": "https://api.github.com/repos/yamadote/phpstorm/events",
    "assignees_url": "https://api.github.com/repos/yamadote/phpstorm/assignees{/user}",
    "branches_url": "https://api.github.com/repos/yamadote/phpstorm/branches{/branch}",
    "tags_url": "https://api.github.com/repos/yamadote/phpstorm/tags",
    "blobs_url": "https://api.github.com/repos/yamadote/phpstorm/git/blobs{/sha}",
    "git_tags_url": "https://api.github.com/repos/yamadote/phpstorm/git/tags{/sha}",
    "git_refs_url": "https://api.github.com/repos/yamadote/phpstorm/git/refs{/sha}",
    "trees_url": "https://api.github.com/repos/yamadote/phpstorm/git/trees{/sha}",
    "statuses_url": "https://api.github.com/repos/yamadote/phpstorm/statuses/{sha}",
    "languages_url": "https://api.github.com/repos/yamadote/phpstorm/languages",
    "stargazers_url": "https://api.github.com/repos/yamadote/phpstorm/stargazers",
    "contributors_url": "https://api.github.com/repos/yamadote/phpstorm/contributors",
    "subscribers_url": "https://api.github.com/repos/yamadote/phpstorm/subscribers",
    "subscription_url": "https://api.github.com/repos/yamadote/phpstorm/subscription",
    "commits_url": "https://api.github.com/repos/yamadote/phpstorm/commits{/sha}",
    "git_commits_url": "https://api.github.com/repos/yamadote/phpstorm/git/commits{/sha}",
    "comments_url": "https://api.github.com/repos/yamadote/phpstorm/comments{/number}",
    "issue_comment_url": "https://api.github.com/repos/yamadote/phpstorm/issues/comments{/number}",
    "contents_url": "https://api.github.com/repos/yamadote/phpstorm/contents/{+path}",
    "compare_url": "https://api.github.com/repos/yamadote/phpstorm/compare/{base}...{head}",
    "merges_url": "https://api.github.com/repos/yamadote/phpstorm/merges",
    "archive_url": "https://api.github.com/repos/yamadote/phpstorm/{archive_format}{/ref}",
    "downloads_url": "https://api.github.com/repos/yamadote/phpstorm/downloads",
    "issues_url": "https://api.github.com/repos/yamadote/phpstorm/issues{/number}",
    "pulls_url": "https://api.github.com/repos/yamadote/phpstorm/pulls{/number}",
    "milestones_url": "https://api.github.com/repos/yamadote/phpstorm/milestones{/number}",
    "notifications_url": "https://api.github.com/repos/yamadote/phpstorm/notifications{?since,all,participating}",
    "labels_url": "https://api.github.com/repos/yamadote/phpstorm/labels{/name}",
    "releases_url": "https://api.github.com/repos/yamadote/phpstorm/releases{/id}",
    "deployments_url": "https://api.github.com/repos/yamadote/phpstorm/deployments",
    "created_at": "2020-08-30T12:57:39Z",
    "updated_at": "2020-09-22T16:51:53Z",
    "pushed_at": "2020-09-22T16:51:51Z",
    "git_url": "git://github.com/yamadote/phpstorm.git",
    "ssh_url": "git@github.com:yamadote/phpstorm.git",
    "clone_url": "https://github.com/yamadote/phpstorm.git",
    "svn_url": "https://github.com/yamadote/phpstorm",
    "homepage": null,
    "size": 6,
    "stargazers_count": 0,
    "watchers_count": 0,
    "language": null,
    "has_issues": true,
    "has_projects": true,
    "has_downloads": true,
    "has_wiki": true,
    "has_pages": false,
    "forks_count": 0,
    "mirror_url": null,
    "archived": false,
    "disabled": false,
    "open_issues_count": 0,
    "license": null,
    "forks": 0,
    "open_issues": 0,
    "watchers": 0,
    "default_branch": "master",
    "permissions": {
      "admin": false,
      "push": false,
      "pull": true
    }
  },
  {
    "id": 183052494,
    "node_id": "MDEwOlJlcG9zaXRvcnkxODMwNTI0OTQ=",
    "name": "resume",
    "full_name": "yamadote/resume",
    "private": false,
    "owner": {
      "login": "yamadote",
      "id": 33160770,
      "node_id": "MDQ6VXNlcjMzMTYwNzcw",
      "avatar_url": "https://avatars.githubusercontent.com/u/33160770?v=4",
      "gravatar_id": "",
      "url": "https://api.github.com/users/yamadote",
      "html_url": "https://github.com/yamadote",
      "followers_url": "https://api.github.com/users/yamadote/followers",
      "following_url": "https://api.github.com/users/yamadote/following{/other_user}",
      "gists_url": "https://api.github.com/users/yamadote/gists{/gist_id}",
      "starred_url": "https://api.github.com/users/yamadote/starred{/owner}{/repo}",
      "subscriptions_url": "https://api.github.com/users/yamadote/subscriptions",
      "organizations_url": "https://api.github.com/users/yamadote/orgs",
      "repos_url": "https://api.github.com/users/yamadote/repos",
      "events_url": "https://api.github.com/users/yamadote/events{/privacy}",
      "received_events_url": "https://api.github.com/users/yamadote/received_events",
      "type": "User",
      "site_admin": false
    },
    "html_url": "https://github.com/yamadote/resume",
    "description": ":sparkles: My special and cool resume",
    "fork": false,
    "url": "https://api.github.com/repos/yamadote/resume",
    "forks_url": "https://api.github.com/repos/yamadote/resume/forks",
    "keys_url": "https://api.github.com/repos/yamadote/resume/keys{/key_id}",
    "collaborators_url": "https://api.github.com/repos/yamadote/resume/collaborators{/collaborator}",
    "teams_url": "https://api.github.com/repos/yamadote/resume/teams",
    "hooks_url": "https://api.github.com/repos/yamadote/resume/hooks",
    "issue_events_url": "https://api.github.com/repos/yamadote/resume/issues/events{/number}",
    "events_url": "https://api.github.com/repos/yamadote/resume/events",
    "assignees_url": "https://api.github.com/repos/yamadote/resume/assignees{/user}",
    "branches_url": "https://api.github.com/repos/yamadote/resume/branches{/branch}",
    "tags_url": "https://api.github.com/repos/yamadote/resume/tags",
    "blobs_url": "https://api.github.com/repos/yamadote/resume/git/blobs{/sha}",
    "git_tags_url": "https://api.github.com/repos/yamadote/resume/git/tags{/sha}",
    "git_refs_url": "https://api.github.com/repos/yamadote/resume/git/refs{/sha}",
    "trees_url": "https://api.github.com/repos/yamadote/resume/git/trees{/sha}",
    "statuses_url": "https://api.github.com/repos/yamadote/resume/statuses/{sha}",
    "languages_url": "https://api.github.com/repos/yamadote/resume/languages",
    "stargazers_url": "https://api.github.com/repos/yamadote/resume/stargazers",
    "contributors_url": "https://api.github.com/repos/yamadote/resume/contributors",
    "subscribers_url": "https://api.github.com/repos/yamadote/resume/subscribers",
    "subscription_url": "https://api.github.com/repos/yamadote/resume/subscription",
    "commits_url": "https://api.github.com/repos/yamadote/resume/commits{/sha}",
    "git_commits_url": "https://api.github.com/repos/yamadote/resume/git/commits{/sha}",
    "comments_url": "https://api.github.com/repos/yamadote/resume/comments{/number}",
    "issue_comment_url": "https://api.github.com/repos/yamadote/resume/issues/comments{/number}",
    "contents_url": "https://api.github.com/repos/yamadote/resume/contents/{+path}",
    "compare_url": "https://api.github.com/repos/yamadote/resume/compare/{base}...{head}",
    "merges_url": "https://api.github.com/repos/yamadote/resume/merges",
    "archive_url": "https://api.github.com/repos/yamadote/resume/{archive_format}{/ref}",
    "downloads_url": "https://api.github.com/repos/yamadote/resume/downloads",
    "issues_url": "https://api.github.com/repos/yamadote/resume/issues{/number}",
    "pulls_url": "https://api.github.com/repos/yamadote/resume/pulls{/number}",
    "milestones_url": "https://api.github.com/repos/yamadote/resume/milestones{/number}",
    "notifications_url": "https://api.github.com/repos/yamadote/resume/notifications{?since,all,participating}",
    "labels_url": "https://api.github.com/repos/yamadote/resume/labels{/name}",
    "releases_url": "https://api.github.com/repos/yamadote/resume/releases{/id}",
    "deployments_url": "https://api.github.com/repos/yamadote/resume/deployments",
    "created_at": "2019-04-23T16:14:46Z",
    "updated_at": "2019-05-13T16:45:37Z",
    "pushed_at": "2019-05-13T16:45:36Z",
    "git_url": "git://github.com/yamadote/resume.git",
    "ssh_url": "git@github.com:yamadote/resume.git",
    "clone_url": "https://github.com/yamadote/resume.git",
    "svn_url": "https://github.com/yamadote/resume",
    "homepage": "https://yamadote.github.io/resume/",
    "size": 3378,
    "stargazers_count": 0,
    "watchers_count": 0,
    "language": "CSS",
    "has_issues": true,
    "has_projects": true,
    "has_downloads": true,
    "has_wiki": true,
    "has_pages": true,
    "forks_count": 0,
    "mirror_url": null,
    "archived": false,
    "disabled": false,
    "open_issues_count": 0,
    "license": {
      "key": "mit",
      "name": "MIT License",
      "spdx_id": "MIT",
      "url": "https://api.github.com/licenses/mit",
      "node_id": "MDc6TGljZW5zZTEz"
    },
    "forks": 0,
    "open_issues": 0,
    "watchers": 0,
    "default_branch": "master",
    "permissions": {
      "admin": false,
      "push": false,
      "pull": true
    }
  },
  {
    "id": 183016718,
    "node_id": "MDEwOlJlcG9zaXRvcnkxODMwMTY3MTg=",
    "name": "simple-blog",
    "full_name": "yamadote/simple-blog",
    "private": false,
    "owner": {
      "login": "yamadote",
      "id": 33160770,
      "node_id": "MDQ6VXNlcjMzMTYwNzcw",
      "avatar_url": "https://avatars.githubusercontent.com/u/33160770?v=4",
      "gravatar_id": "",
      "url": "https://api.github.com/users/yamadote",
      "html_url": "https://github.com/yamadote",
      "followers_url": "https://api.github.com/users/yamadote/followers",
      "following_url": "https://api.github.com/users/yamadote/following{/other_user}",
      "gists_url": "https://api.github.com/users/yamadote/gists{/gist_id}",
      "starred_url": "https://api.github.com/users/yamadote/starred{/owner}{/repo}",
      "subscriptions_url": "https://api.github.com/users/yamadote/subscriptions",
      "organizations_url": "https://api.github.com/users/yamadote/orgs",
      "repos_url": "https://api.github.com/users/yamadote/repos",
      "events_url": "https://api.github.com/users/yamadote/events{/privacy}",
      "received_events_url": "https://api.github.com/users/yamadote/received_events",
      "type": "User",
      "site_admin": false
    },
    "html_url": "https://github.com/yamadote/simple-blog",
    "description": ":green_book: This is a blog developed with Symfony + Twig",
    "fork": false,
    "url": "https://api.github.com/repos/yamadote/simple-blog",
    "forks_url": "https://api.github.com/repos/yamadote/simple-blog/forks",
    "keys_url": "https://api.github.com/repos/yamadote/simple-blog/keys{/key_id}",
    "collaborators_url": "https://api.github.com/repos/yamadote/simple-blog/collaborators{/collaborator}",
    "teams_url": "https://api.github.com/repos/yamadote/simple-blog/teams",
    "hooks_url": "https://api.github.com/repos/yamadote/simple-blog/hooks",
    "issue_events_url": "https://api.github.com/repos/yamadote/simple-blog/issues/events{/number}",
    "events_url": "https://api.github.com/repos/yamadote/simple-blog/events",
    "assignees_url": "https://api.github.com/repos/yamadote/simple-blog/assignees{/user}",
    "branches_url": "https://api.github.com/repos/yamadote/simple-blog/branches{/branch}",
    "tags_url": "https://api.github.com/repos/yamadote/simple-blog/tags",
    "blobs_url": "https://api.github.com/repos/yamadote/simple-blog/git/blobs{/sha}",
    "git_tags_url": "https://api.github.com/repos/yamadote/simple-blog/git/tags{/sha}",
    "git_refs_url": "https://api.github.com/repos/yamadote/simple-blog/git/refs{/sha}",
    "trees_url": "https://api.github.com/repos/yamadote/simple-blog/git/trees{/sha}",
    "statuses_url": "https://api.github.com/repos/yamadote/simple-blog/statuses/{sha}",
    "languages_url": "https://api.github.com/repos/yamadote/simple-blog/languages",
    "stargazers_url": "https://api.github.com/repos/yamadote/simple-blog/stargazers",
    "contributors_url": "https://api.github.com/repos/yamadote/simple-blog/contributors",
    "subscribers_url": "https://api.github.com/repos/yamadote/simple-blog/subscribers",
    "subscription_url": "https://api.github.com/repos/yamadote/simple-blog/subscription",
    "commits_url": "https://api.github.com/repos/yamadote/simple-blog/commits{/sha}",
    "git_commits_url": "https://api.github.com/repos/yamadote/simple-blog/git/commits{/sha}",
    "comments_url": "https://api.github.com/repos/yamadote/simple-blog/comments{/number}",
    "issue_comment_url": "https://api.github.com/repos/yamadote/simple-blog/issues/comments{/number}",
    "contents_url": "https://api.github.com/repos/yamadote/simple-blog/contents/{+path}",
    "compare_url": "https://api.github.com/repos/yamadote/simple-blog/compare/{base}...{head}",
    "merges_url": "https://api.github.com/repos/yamadote/simple-blog/merges",
    "archive_url": "https://api.github.com/repos/yamadote/simple-blog/{archive_format}{/ref}",
    "downloads_url": "https://api.github.com/repos/yamadote/simple-blog/downloads",
    "issues_url": "https://api.github.com/repos/yamadote/simple-blog/issues{/number}",
    "pulls_url": "https://api.github.com/repos/yamadote/simple-blog/pulls{/number}",
    "milestones_url": "https://api.github.com/repos/yamadote/simple-blog/milestones{/number}",
    "notifications_url": "https://api.github.com/repos/yamadote/simple-blog/notifications{?since,all,participating}",
    "labels_url": "https://api.github.com/repos/yamadote/simple-blog/labels{/name}",
    "releases_url": "https://api.github.com/repos/yamadote/simple-blog/releases{/id}",
    "deployments_url": "https://api.github.com/repos/yamadote/simple-blog/deployments",
    "created_at": "2019-04-23T13:04:49Z",
    "updated_at": "2019-05-13T16:26:35Z",
    "pushed_at": "2019-05-13T16:26:33Z",
    "git_url": "git://github.com/yamadote/simple-blog.git",
    "ssh_url": "git@github.com:yamadote/simple-blog.git",
    "clone_url": "https://github.com/yamadote/simple-blog.git",
    "svn_url": "https://github.com/yamadote/simple-blog",
    "homepage": "",
    "size": 1716,
    "stargazers_count": 0,
    "watchers_count": 0,
    "language": "PHP",
    "has_issues": true,
    "has_projects": true,
    "has_downloads": true,
    "has_wiki": true,
    "has_pages": false,
    "forks_count": 0,
    "mirror_url": null,
    "archived": false,
    "disabled": false,
    "open_issues_count": 0,
    "license": {
      "key": "mit",
      "name": "MIT License",
      "spdx_id": "MIT",
      "url": "https://api.github.com/licenses/mit",
      "node_id": "MDc6TGljZW5zZTEz"
    },
    "forks": 0,
    "open_issues": 0,
    "watchers": 0,
    "default_branch": "master",
    "permissions": {
      "admin": false,
      "push": false,
      "pull": true
    }
  },
  {
    "id": 256807415,
    "node_id": "MDEwOlJlcG9zaXRvcnkyNTY4MDc0MTU=",
    "name": "time-tracker",
    "full_name": "yamadote/time-tracker",
    "private": false,
    "owner": {
      "login": "yamadote",
      "id": 33160770,
      "node_id": "MDQ6VXNlcjMzMTYwNzcw",
      "avatar_url": "https://avatars.githubusercontent.com/u/33160770?v=4",
      "gravatar_id": "",
      "url": "https://api.github.com/users/yamadote",
      "html_url": "https://github.com/yamadote",
      "followers_url": "https://api.github.com/users/yamadote/followers",
      "following_url": "https://api.github.com/users/yamadote/following{/other_user}",
      "gists_url": "https://api.github.com/users/yamadote/gists{/gist_id}",
      "starred_url": "https://api.github.com/users/yamadote/starred{/owner}{/repo}",
      "subscriptions_url": "https://api.github.com/users/yamadote/subscriptions",
      "organizations_url": "https://api.github.com/users/yamadote/orgs",
      "repos_url": "https://api.github.com/users/yamadote/repos",
      "events_url": "https://api.github.com/users/yamadote/events{/privacy}",
      "received_events_url": "https://api.github.com/users/yamadote/received_events",
      "type": "User",
      "site_admin": false
    },
    "html_url": "https://github.com/yamadote/time-tracker",
    "description": ":zap: Just time traking app.",
    "fork": false,
    "url": "https://api.github.com/repos/yamadote/time-tracker",
    "forks_url": "https://api.github.com/repos/yamadote/time-tracker/forks",
    "keys_url": "https://api.github.com/repos/yamadote/time-tracker/keys{/key_id}",
    "collaborators_url": "https://api.github.com/repos/yamadote/time-tracker/collaborators{/collaborator}",
    "teams_url": "https://api.github.com/repos/yamadote/time-tracker/teams",
    "hooks_url": "https://api.github.com/repos/yamadote/time-tracker/hooks",
    "issue_events_url": "https://api.github.com/repos/yamadote/time-tracker/issues/events{/number}",
    "events_url": "https://api.github.com/repos/yamadote/time-tracker/events",
    "assignees_url": "https://api.github.com/repos/yamadote/time-tracker/assignees{/user}",
    "branches_url": "https://api.github.com/repos/yamadote/time-tracker/branches{/branch}",
    "tags_url": "https://api.github.com/repos/yamadote/time-tracker/tags",
    "blobs_url": "https://api.github.com/repos/yamadote/time-tracker/git/blobs{/sha}",
    "git_tags_url": "https://api.github.com/repos/yamadote/time-tracker/git/tags{/sha}",
    "git_refs_url": "https://api.github.com/repos/yamadote/time-tracker/git/refs{/sha}",
    "trees_url": "https://api.github.com/repos/yamadote/time-tracker/git/trees{/sha}",
    "statuses_url": "https://api.github.com/repos/yamadote/time-tracker/statuses/{sha}",
    "languages_url": "https://api.github.com/repos/yamadote/time-tracker/languages",
    "stargazers_url": "https://api.github.com/repos/yamadote/time-tracker/stargazers",
    "contributors_url": "https://api.github.com/repos/yamadote/time-tracker/contributors",
    "subscribers_url": "https://api.github.com/repos/yamadote/time-tracker/subscribers",
    "subscription_url": "https://api.github.com/repos/yamadote/time-tracker/subscription",
    "commits_url": "https://api.github.com/repos/yamadote/time-tracker/commits{/sha}",
    "git_commits_url": "https://api.github.com/repos/yamadote/time-tracker/git/commits{/sha}",
    "comments_url": "https://api.github.com/repos/yamadote/time-tracker/comments{/number}",
    "issue_comment_url": "https://api.github.com/repos/yamadote/time-tracker/issues/comments{/number}",
    "contents_url": "https://api.github.com/repos/yamadote/time-tracker/contents/{+path}",
    "compare_url": "https://api.github.com/repos/yamadote/time-tracker/compare/{base}...{head}",
    "merges_url": "https://api.github.com/repos/yamadote/time-tracker/merges",
    "archive_url": "https://api.github.com/repos/yamadote/time-tracker/{archive_format}{/ref}",
    "downloads_url": "https://api.github.com/repos/yamadote/time-tracker/downloads",
    "issues_url": "https://api.github.com/repos/yamadote/time-tracker/issues{/number}",
    "pulls_url": "https://api.github.com/repos/yamadote/time-tracker/pulls{/number}",
    "milestones_url": "https://api.github.com/repos/yamadote/time-tracker/milestones{/number}",
    "notifications_url": "https://api.github.com/repos/yamadote/time-tracker/notifications{?since,all,participating}",
    "labels_url": "https://api.github.com/repos/yamadote/time-tracker/labels{/name}",
    "releases_url": "https://api.github.com/repos/yamadote/time-tracker/releases{/id}",
    "deployments_url": "https://api.github.com/repos/yamadote/time-tracker/deployments",
    "created_at": "2020-04-18T17:01:27Z",
    "updated_at": "2020-04-18T17:22:54Z",
    "pushed_at": "2020-04-18T17:22:52Z",
    "git_url": "git://github.com/yamadote/time-tracker.git",
    "ssh_url": "git@github.com:yamadote/time-tracker.git",
    "clone_url": "https://github.com/yamadote/time-tracker.git",
    "svn_url": "https://github.com/yamadote/time-tracker",
    "homepage": "",
    "size": 0,
    "stargazers_count": 0,
    "watchers_count": 0,
    "language": null,
    "has_issues": true,
    "has_projects": true,
    "has_downloads": true,
    "has_wiki": true,
    "has_pages": false,
    "forks_count": 0,
    "mirror_url": null,
    "archived": false,
    "disabled": false,
    "open_issues_count": 0,
    "license": null,
    "forks": 0,
    "open_issues": 0,
    "watchers": 0,
    "default_branch": "master",
    "permissions": {
      "admin": false,
      "push": false,
      "pull": true
    }
  }
]